opsgw_sdk/__init__.py
opsgw_sdk/client.py
opsgw_sdk/exceptions.py
opsgw_sdk/health_checker.py
opsgw_sdk-1.0.1.dist-info/licenses/LICENSE
opsgw_sdk-1.0.1.dist-info/METADATA
opsgw_sdk-1.0.1.dist-info/WHEEL
opsgw_sdk-1.0.1.dist-info/top_level.txt
opsgw_sdk-1.0.1.dist-info/RECORD
