Metadata-Version: 2.4
Name: opsgw-sdk
Version: 1.0.1
Summary: 具有健康监测功能的HTTP SDK
Home-page: https://github.com/opsgw/opsgw-sdk-python
Author: OpsGW Team
Author-email: team@opsgw.com
Project-URL: Bug Reports, https://github.com/opsgw/opsgw-sdk-python/issues
Project-URL: Source, https://github.com/opsgw/opsgw-sdk-python
Project-URL: Documentation, https://github.com/opsgw/opsgw-sdk-python/blob/main/README.md
Keywords: http client sdk health check dns load balancer
Classifier: Development Status :: 4 - Beta
Classifier: Intended Audience :: Developers
Classifier: License :: OSI Approved :: MIT License
Classifier: Operating System :: OS Independent
Classifier: Programming Language :: Python :: 3
Classifier: Programming Language :: Python :: 3.7
Classifier: Programming Language :: Python :: 3.8
Classifier: Programming Language :: Python :: 3.9
Classifier: Programming Language :: Python :: 3.10
Classifier: Programming Language :: Python :: 3.11
Classifier: Programming Language :: Python :: 3.12
Classifier: Programming Language :: Python :: 3.13
Classifier: Topic :: Internet :: WWW/HTTP
Classifier: Topic :: Software Development :: Libraries :: Python Modules
Requires-Python: >=3.7
License-File: LICENSE
Requires-Dist: requests>=2.31.0
Requires-Dist: dnspython>=2.4.0
Requires-Dist: aiohttp>=3.8.0
Requires-Dist: asyncio-throttle>=1.0.0
Provides-Extra: dev
Requires-Dist: pytest>=6.0; extra == "dev"
Requires-Dist: pytest-asyncio>=0.18.0; extra == "dev"
Requires-Dist: pytest-cov>=2.10; extra == "dev"
Requires-Dist: black>=21.0; extra == "dev"
Requires-Dist: flake8>=3.8; extra == "dev"
Requires-Dist: mypy>=0.800; extra == "dev"
Dynamic: author
Dynamic: author-email
Dynamic: classifier
Dynamic: description
Dynamic: description-content-type
Dynamic: home-page
Dynamic: keywords
Dynamic: license-file
Dynamic: project-url
Dynamic: provides-extra
Dynamic: requires-dist
Dynamic: requires-python
Dynamic: summary
